[
    { 
        "id": "1a2b3c4d-0001-0000-0000-000000000001",
        "title": "Software Engineer",
        "company_name": "TechCorp",
        "location": "Cairo, Egypt",
        "salary": "EGP 15,000 - 20,000",
        "job_type": "Full-time",
        "description": "Develop and maintain web applications.",
        "requirements": "3+ years experience in software development, knowledge of Python and JavaScript.",
        "contact_email": "hr@techcorp.com",
        "date_posted": "2025-08-01"
    },
    {
        "id": "1a2b3c4d-0002-0000-0000-000000000002",
        "title": "Data Scientist",
        "company_name": "AI Solutions",
        "location": "Alexandria, Egypt",
        "salary": "EGP 18,000 - 25,000",
        "job_type": "Full-time",
        "description": "Analyze data and build predictive models to support business decisions.",
        "requirements": "2+ years experience in machine learning, proficiency in Python, SQL, and TensorFlow.",
        "contact_email": "careers@aisolutions.com",
        "date_posted": "2025-07-28"
    },
    {
        "id": "1a2b3c4d-0003-0000-0000-000000000003",
        "title": "Frontend Developer",
        "company_name": "Webify",
        "location": "Remote",
        "salary": "EGP 12,000 - 18,000",
        "job_type": "Part-time",
        "description": "Create and maintain responsive user interfaces.",
        "requirements": "Experience with React, HTML, CSS, and responsive design.",
        "contact_email": "jobs@webify.com",
        "date_posted": "2025-08-05"
    },
    {
        "id": "1a2b3c4d-0004-0000-0000-000000000004",
        "title": "Backend Developer",
        "company_name": "CloudNet",
        "location": "Giza, Egypt",
        "salary": "EGP 14,000 - 19,000",
        "job_type": "Full-time",
        "description": "Build scalable APIs and manage cloud infrastructure.",
        "requirements": "Strong knowledge of Node.js, databases, and cloud services (AWS/Azure).",
        "contact_email": "hiring@cloudnet.com",
        "date_posted": "2025-08-10"
    },
    {
        "id": "1a2b3c4d-0005-0000-0000-000000000005",
        "title": "UI/UX Designer",
        "company_name": "Creative Minds",
        "location": "Cairo, Egypt",
        "salary": "EGP 10,000 - 15,000",
        "job_type": "Full-time",
        "description": "Design user-friendly and visually appealing web and mobile interfaces.",
        "requirements": "Experience in Figma, Adobe XD, and a strong portfolio of design projects.",
        "contact_email": "design@creativeminds.com",
        "date_posted": "2025-07-30"
    }
]
